<?xml version="1.0" encoding="utf-8"?>
<resources>
    <games>
        <game>
            <game_id>1</game_id>
            <game_minigameID>1</game_minigameID>
            <game_max_score>0</game_max_score>
            <game_stars>0</game_stars>
            <game_actual_position>
                <game_actual_position_x>0</game_actual_position_x>
                <game_actual_position_y>0</game_actual_position_y>
            </game_actual_position>
            <game_estado>1</game_estado>
        </game>
        <game>
            <game_id>2</game_id>
            <game_minigameID>2</game_minigameID>
            <game_max_score>0</game_max_score>
            <game_stars>0</game_stars>
            <game_actual_position>
                <game_actual_position_x>0</game_actual_position_x>
                <game_actual_position_y>0</game_actual_position_y>
            </game_actual_position>
            <game_estado>1</game_estado>
        </game>
    </games>
</resources>
